[
                {
                                "name": "Fernando",
                                "lastName": "Kobata",
                                "mail": "flucastj@outlook.com",
                                "datetimeCad": "",
                                "docNum": "33918297888",
                                "username": "flrfonse",
                                "txtsenha": "Kob@ta0-21",
                                "Country": "Brasil",
                                "state": "SP",
                                "city": "S\u00e3o Jos\u00e9 dos Campos",
                                "CEP": "12042490",
                                "Adress": "pra\u00e7a jos\u00e9 luiz da costa ferreira",
                                "numberAdress": "289",
                                "phone": "12996394042"
                },
                {
                                "name": "Rafaela",
                                "lastName": "Leite",
                                "mail": "rafaLeite@gmail.com",
                                "datetimeCad": "2024-03-12",
                                "docNum": "9999999999",
                                "username": "rfleite",
                                "txtsenha": "357258",
                                "Country": "Brasil",
                                "state": "SP",
                                "city": "S\u00e3o Jos\u00e9 dos Campos",
                                "CEP": "12042490",
                                "Adress": "pra\u00e7a jos\u00e9 luiz da costa ferreira",
                                "numberAdress": "289",
                                "phone": "12996394042"
                }
]